MANIFEST.in
README.rst
setup.py
aliyun_python_sdk_sas_api.egg-info/PKG-INFO
aliyun_python_sdk_sas_api.egg-info/SOURCES.txt
aliyun_python_sdk_sas_api.egg-info/dependency_links.txt
aliyun_python_sdk_sas_api.egg-info/requires.txt
aliyun_python_sdk_sas_api.egg-info/top_level.txt
aliyunsdksas_api/__init__.py
aliyunsdksas_api/request/__init__.py
aliyunsdksas_api/request/v20170705/DescribeAccountProfileByKeyRequest.py
aliyunsdksas_api/request/v20170705/DescribeAccountProfileByKeyWordRequest.py
aliyunsdksas_api/request/v20170705/DescribeHitRateColumnRequest.py
aliyunsdksas_api/request/v20170705/DescribeHitRatePieRequest.py
aliyunsdksas_api/request/v20170705/DescribePerDateDataRequest.py
aliyunsdksas_api/request/v20170705/DescribeThreatDistributeRequest.py
aliyunsdksas_api/request/v20170705/DescribeThreatTypeLinesRequest.py
aliyunsdksas_api/request/v20170705/DescribeTotalAndRateLineRequest.py
aliyunsdksas_api/request/v20170705/GetAccountProfileRequest.py
aliyunsdksas_api/request/v20170705/GetInstanceCountRequest.py
aliyunsdksas_api/request/v20170705/GetIpProfileRequest.py
aliyunsdksas_api/request/v20170705/GetPhoneProfileRequest.py
aliyunsdksas_api/request/v20170705/__init__.py